pretty_cli_logger/__init__.py
pretty_cli_logger/colors.py
pretty_cli_logger/main.py
pretty_cli_logger-1.1.2.dist-info/licenses/LICENSE
pretty_cli_logger-1.1.2.dist-info/METADATA
pretty_cli_logger-1.1.2.dist-info/WHEEL
pretty_cli_logger-1.1.2.dist-info/top_level.txt
pretty_cli_logger-1.1.2.dist-info/RECORD
