Metadata-Version: 2.4
Name: pretty-cli-logger
Version: 1.1.2
Summary: Zero-dependency colorful CLI logger
Author: Oscar Harvey
Author-email: <oscar.harvey371@gmail.com>
License: Apache-2.0
Keywords: logger,pretty,cli-logger,pretty-cli-logger
Classifier: Intended Audience :: Developers
Classifier: Development Status :: 5 - Production/Stable
Classifier: Programming Language :: Python :: 3
Classifier: Programming Language :: Python :: 3.9
Classifier: Programming Language :: Python :: 3.10
Classifier: Programming Language :: Python :: 3.11
Classifier: Programming Language :: Python :: 3.12
Classifier: Programming Language :: Python :: 3.13
License-File: LICENSE
Dynamic: author
Dynamic: author-email
Dynamic: classifier
Dynamic: description
Dynamic: description-content-type
Dynamic: keywords
Dynamic: license
Dynamic: license-file
Dynamic: summary
